simplypy/__init__.py
simplypy/myfunctions.py
simplypy-0.1.0.dist-info/LICENSE
simplypy-0.1.0.dist-info/METADATA
simplypy-0.1.0.dist-info/WHEEL
simplypy-0.1.0.dist-info/top_level.txt
simplypy-0.1.0.dist-info/RECORD
