Metadata-Version: 2.1
Name: simplypy
Version: 0.1.0
Summary: My first Python library
Author: Hrithik_Sagar
License-File: LICENSE
